README.rst
setup.py
./docker_registry_client.py
docker_registry_admin.egg-info/PKG-INFO
docker_registry_admin.egg-info/SOURCES.txt
docker_registry_admin.egg-info/dependency_links.txt
docker_registry_admin.egg-info/entry_points.txt
docker_registry_admin.egg-info/requires.txt
docker_registry_admin.egg-info/top_level.txt