Metadata-Version: 1.1
Name: docker-registry-admin
Version: 1.0.1
Summary: A convenience script to list and delete registries from docker registry.
Home-page: https://github.com/frederico-apolonia/Docker-Registry-Client
Author: Frederico Apolonia
Author-email: fredericojcapolo@gmail.com
License: MIT
Keywords: docker registry
Platform: UNKNOWN
Classifier: Development Status :: 3 - Alpha
Classifier: License :: OSI Approved :: MIT License
Classifier: Programming Language :: Python :: 3.7
